{
  "session_id": "test-1769108878243",
  "consultations": [
    {
      "timestamp": "2026-01-22T19:07:58.243Z",
      "query": "Query 1",
      "sources_checked": [
        {
          "type": "glob",
          "pattern": "**/*.ts",
          "files_matched": 5
        },
        {
          "type": "grep",
          "pattern": "function",
          "count": 3
        }
      ],
      "key_findings": [
        "finding1",
        "finding2",
        "finding3"
      ]
    },
    {
      "timestamp": "2026-01-22T19:06:58.243Z",
      "query": "Query 2",
      "sources_checked": [
        {
          "type": "glob",
          "pattern": "**/*.ts",
          "files_matched": 5
        },
        {
          "type": "grep",
          "pattern": "function",
          "count": 3
        }
      ],
      "key_findings": [
        "finding1",
        "finding2",
        "finding3"
      ]
    },
    {
      "timestamp": "2026-01-22T19:05:58.243Z",
      "query": "Query 3",
      "sources_checked": [
        {
          "type": "glob",
          "pattern": "**/*.ts",
          "files_matched": 5
        },
        {
          "type": "grep",
          "pattern": "function",
          "count": 3
        }
      ],
      "key_findings": [
        "finding1",
        "finding2",
        "finding3"
      ]
    },
    {
      "timestamp": "2026-01-22T19:04:58.243Z",
      "query": "Query 4",
      "sources_checked": [
        {
          "type": "glob",
          "pattern": "**/*.ts",
          "files_matched": 5
        },
        {
          "type": "grep",
          "pattern": "function",
          "count": 3
        }
      ],
      "key_findings": [
        "finding1",
        "finding2",
        "finding3"
      ]
    },
    {
      "timestamp": "2026-01-22T19:03:58.243Z",
      "query": "Query 5",
      "sources_checked": [
        {
          "type": "glob",
          "pattern": "**/*.ts",
          "files_matched": 5
        },
        {
          "type": "grep",
          "pattern": "function",
          "count": 3
        }
      ],
      "key_findings": [
        "finding1",
        "finding2",
        "finding3"
      ]
    },
    {
      "timestamp": "2026-01-22T19:02:58.243Z",
      "query": "Query 6",
      "sources_checked": [
        {
          "type": "glob",
          "pattern": "**/*.ts",
          "files_matched": 5
        },
        {
          "type": "grep",
          "pattern": "function",
          "count": 3
        }
      ],
      "key_findings": [
        "finding1",
        "finding2",
        "finding3"
      ]
    },
    {
      "timestamp": "2026-01-22T19:01:58.243Z",
      "query": "Query 7",
      "sources_checked": [
        {
          "type": "glob",
          "pattern": "**/*.ts",
          "files_matched": 5
        },
        {
          "type": "grep",
          "pattern": "function",
          "count": 3
        }
      ],
      "key_findings": [
        "finding1",
        "finding2",
        "finding3"
      ]
    },
    {
      "timestamp": "2026-01-22T19:00:58.243Z",
      "query": "Query 8",
      "sources_checked": [
        {
          "type": "glob",
          "pattern": "**/*.ts",
          "files_matched": 5
        },
        {
          "type": "grep",
          "pattern": "function",
          "count": 3
        }
      ],
      "key_findings": [
        "finding1",
        "finding2",
        "finding3"
      ]
    },
    {
      "timestamp": "2026-01-22T18:59:58.243Z",
      "query": "Query 9",
      "sources_checked": [
        {
          "type": "glob",
          "pattern": "**/*.ts",
          "files_matched": 5
        },
        {
          "type": "grep",
          "pattern": "function",
          "count": 3
        }
      ],
      "key_findings": [
        "finding1",
        "finding2",
        "finding3"
      ]
    },
    {
      "timestamp": "2026-01-22T18:58:58.243Z",
      "query": "Query 10",
      "sources_checked": [
        {
          "type": "glob",
          "pattern": "**/*.ts",
          "files_matched": 5
        },
        {
          "type": "grep",
          "pattern": "function",
          "count": 3
        }
      ],
      "key_findings": [
        "finding1",
        "finding2",
        "finding3"
      ]
    },
    {
      "timestamp": "2026-01-22T18:57:58.243Z",
      "query": "Query 11",
      "sources_checked": [
        {
          "type": "glob",
          "pattern": "**/*.ts",
          "files_matched": 5
        },
        {
          "type": "grep",
          "pattern": "function",
          "count": 3
        }
      ],
      "key_findings": [
        "finding1",
        "finding2",
        "finding3"
      ]
    },
    {
      "timestamp": "2026-01-22T18:56:58.243Z",
      "query": "Query 12",
      "sources_checked": [
        {
          "type": "glob",
          "pattern": "**/*.ts",
          "files_matched": 5
        },
        {
          "type": "grep",
          "pattern": "function",
          "count": 3
        }
      ],
      "key_findings": [
        "finding1",
        "finding2",
        "finding3"
      ]
    },
    {
      "timestamp": "2026-01-22T18:55:58.243Z",
      "query": "Query 13",
      "sources_checked": [
        {
          "type": "glob",
          "pattern": "**/*.ts",
          "files_matched": 5
        },
        {
          "type": "grep",
          "pattern": "function",
          "count": 3
        }
      ],
      "key_findings": [
        "finding1",
        "finding2",
        "finding3"
      ]
    },
    {
      "timestamp": "2026-01-22T18:54:58.243Z",
      "query": "Query 14",
      "sources_checked": [
        {
          "type": "glob",
          "pattern": "**/*.ts",
          "files_matched": 5
        },
        {
          "type": "grep",
          "pattern": "function",
          "count": 3
        }
      ],
      "key_findings": [
        "finding1",
        "finding2",
        "finding3"
      ]
    },
    {
      "timestamp": "2026-01-22T18:53:58.243Z",
      "query": "Query 15",
      "sources_checked": [
        {
          "type": "glob",
          "pattern": "**/*.ts",
          "files_matched": 5
        },
        {
          "type": "grep",
          "pattern": "function",
          "count": 3
        }
      ],
      "key_findings": [
        "finding1",
        "finding2",
        "finding3"
      ]
    },
    {
      "timestamp": "2026-01-22T18:52:58.243Z",
      "query": "Query 16",
      "sources_checked": [
        {
          "type": "glob",
          "pattern": "**/*.ts",
          "files_matched": 5
        },
        {
          "type": "grep",
          "pattern": "function",
          "count": 3
        }
      ],
      "key_findings": [
        "finding1",
        "finding2",
        "finding3"
      ]
    },
    {
      "timestamp": "2026-01-22T18:51:58.243Z",
      "query": "Query 17",
      "sources_checked": [
        {
          "type": "glob",
          "pattern": "**/*.ts",
          "files_matched": 5
        },
        {
          "type": "grep",
          "pattern": "function",
          "count": 3
        }
      ],
      "key_findings": [
        "finding1",
        "finding2",
        "finding3"
      ]
    },
    {
      "timestamp": "2026-01-22T18:50:58.243Z",
      "query": "Query 18",
      "sources_checked": [
        {
          "type": "glob",
          "pattern": "**/*.ts",
          "files_matched": 5
        },
        {
          "type": "grep",
          "pattern": "function",
          "count": 3
        }
      ],
      "key_findings": [
        "finding1",
        "finding2",
        "finding3"
      ]
    },
    {
      "timestamp": "2026-01-22T18:49:58.243Z",
      "query": "Query 19",
      "sources_checked": [
        {
          "type": "glob",
          "pattern": "**/*.ts",
          "files_matched": 5
        },
        {
          "type": "grep",
          "pattern": "function",
          "count": 3
        }
      ],
      "key_findings": [
        "finding1",
        "finding2",
        "finding3"
      ]
    },
    {
      "timestamp": "2026-01-22T18:48:58.243Z",
      "query": "Query 20",
      "sources_checked": [
        {
          "type": "glob",
          "pattern": "**/*.ts",
          "files_matched": 5
        },
        {
          "type": "grep",
          "pattern": "function",
          "count": 3
        }
      ],
      "key_findings": [
        "finding1",
        "finding2",
        "finding3"
      ]
    }
  ]
}